<?xml version="1.0" encoding="utf-8"?>
<statistics>
<info><vm-name>fizica</vm-name><bandwidth>100</bandwidth><totalSend>24</totalSend><totalRecv>52</totalRecv><proto_details><ip><totalPacketsReceived>42</totalPacketsReceived><inAddrErrors>0</inAddrErrors><incomingPacketsDiscarded>0</incomingPacketsDiscarded><incomingPacketsDelivered>24</incomingPacketsDelivered><requestsSentOut>24</requestsSentOut><outgoingDropped>0</outgoingDropped><reasmTimeout>0</reasmTimeout><reasmReqds>0</reasmReqds><reasmOKs>0</reasmOKs><reasmFails>0</reasmFails><fragOKs>0</fragOKs><fragFails>0</fragFails><fragCreates>0</fragCreates></ip><tcp><activeConnections>373</activeConnections><failedConnections>59</failedConnections><segmentsRecv>24</segmentsRecv><segmentsSend>24</segmentsSend><badSegments>0</badSegments><resetsSent>0</resetsSent></tcp><udp><packetsReceived>0</packetsReceived><unknownPortRecv>0</unknownPortRecv><recvErrors>0</recvErrors><packetsSent>0</packetsSent></udp></proto_details><resources><Memory_used>57.51248795731831</Memory_used><MaxMemoryUsed>57.53234320226038</MaxMemoryUsed><MemOverThreshold>0</MemOverThreshold><CPU_used>0</CPU_used><MaxCpuAvg>0</MaxCpuAvg><CpuOverThreshold>0</CpuOverThreshold><Interrupts>0</Interrupts></resources><socket><established>6</established><listening>24</listening><connected>413</connected></socket><tracepoints><kfree_skb>132</kfree_skb><consume_skb>322</consume_skb></tracepoints></info>
<info><vm-name>fizica</vm-name><bandwidth>200</bandwidth><totalSend>24</totalSend><totalRecv>52</totalRecv><proto_details><ip><totalPacketsReceived>42</totalPacketsReceived><inAddrErrors>0</inAddrErrors><incomingPacketsDiscarded>0</incomingPacketsDiscarded><incomingPacketsDelivered>24</incomingPacketsDelivered><requestsSentOut>24</requestsSentOut><outgoingDropped>0</outgoingDropped><reasmTimeout>0</reasmTimeout><reasmReqds>0</reasmReqds><reasmOKs>0</reasmOKs><reasmFails>0</reasmFails><fragOKs>0</fragOKs><fragFails>0</fragFails><fragCreates>0</fragCreates></ip><tcp><activeConnections>373</activeConnections><failedConnections>59</failedConnections><segmentsRecv>24</segmentsRecv><segmentsSend>24</segmentsSend><badSegments>0</badSegments><resetsSent>0</resetsSent></tcp><udp><packetsReceived>0</packetsReceived><unknownPortRecv>0</unknownPortRecv><recvErrors>0</recvErrors><packetsSent>0</packetsSent></udp></proto_details><resources><Memory_used>57.51248795731831</Memory_used><MaxMemoryUsed>57.53234320226038</MaxMemoryUsed><MemOverThreshold>0</MemOverThreshold><CPU_used>0</CPU_used><MaxCpuAvg>0</MaxCpuAvg><CpuOverThreshold>0</CpuOverThreshold><Interrupts>0</Interrupts></resources><socket><established>6</established><listening>24</listening><connected>413</connected></socket><tracepoints><kfree_skb>132</kfree_skb><consume_skb>322</consume_skb></tracepoints></info>
<info><vm-name>fizica</vm-name><bandwidth>300</bandwidth><totalSend>24</totalSend><totalRecv>52</totalRecv><proto_details><ip><totalPacketsReceived>42</totalPacketsReceived><inAddrErrors>0</inAddrErrors><incomingPacketsDiscarded>0</incomingPacketsDiscarded><incomingPacketsDelivered>24</incomingPacketsDelivered><requestsSentOut>24</requestsSentOut><outgoingDropped>0</outgoingDropped><reasmTimeout>0</reasmTimeout><reasmReqds>0</reasmReqds><reasmOKs>0</reasmOKs><reasmFails>0</reasmFails><fragOKs>0</fragOKs><fragFails>0</fragFails><fragCreates>0</fragCreates></ip><tcp><activeConnections>373</activeConnections><failedConnections>59</failedConnections><segmentsRecv>24</segmentsRecv><segmentsSend>24</segmentsSend><badSegments>0</badSegments><resetsSent>0</resetsSent></tcp><udp><packetsReceived>0</packetsReceived><unknownPortRecv>0</unknownPortRecv><recvErrors>0</recvErrors><packetsSent>0</packetsSent></udp></proto_details><resources><Memory_used>57.51248795731831</Memory_used><MaxMemoryUsed>57.53234320226038</MaxMemoryUsed><MemOverThreshold>0</MemOverThreshold><CPU_used>0</CPU_used><MaxCpuAvg>0</MaxCpuAvg><CpuOverThreshold>0</CpuOverThreshold><Interrupts>0</Interrupts></resources><socket><established>6</established><listening>24</listening><connected>413</connected></socket><tracepoints><kfree_skb>132</kfree_skb><consume_skb>322</consume_skb></tracepoints></info>
</statistics>
